sql_compare/__init__.py
sql_compare/py.typed
sql_compare-0.1.9.dist-info/LICENSE
sql_compare-0.1.9.dist-info/METADATA
sql_compare-0.1.9.dist-info/WHEEL
sql_compare-0.1.9.dist-info/RECORD
