Metadata-Version: 2.3
Name: sql-compare
Version: 0.1.9
Summary: Compare SQL schemas
License: Apache-2.0
Keywords: sql,database,schema,compare,diff,migration
Author: Charly Laurent
Author-email: charly.laurent@mergify.com
Maintainer: Mergify
Maintainer-email: engineering@mergify.com
Requires-Python: >=3.9
Classifier: Development Status :: 5 - Production/Stable
Classifier: Intended Audience :: Developers
Classifier: License :: OSI Approved :: Apache Software License
Classifier: Natural Language :: English
Classifier: Operating System :: OS Independent
Classifier: Programming Language :: Python
Classifier: Programming Language :: Python :: 3
Classifier: Programming Language :: Python :: 3 :: Only
Classifier: Programming Language :: Python :: 3.9
Classifier: Programming Language :: Python :: 3.10
Classifier: Programming Language :: Python :: 3.11
Classifier: Programming Language :: Python :: 3.12
Classifier: Programming Language :: Python :: Implementation :: CPython
Classifier: Programming Language :: Python :: Implementation :: PyPy
Classifier: Topic :: Database
Classifier: Topic :: Software Development
Classifier: Topic :: Software Development :: Testing
Classifier: Topic :: Software Development :: Testing :: Unit
Requires-Dist: sqlparse (>=0.5.0)
Project-URL: Bug Tracker, https://github.com/Mergifyio/sql-compare/issues
Project-URL: Repository, https://github.com/Mergifyio/sql-compare
